_raw/vhdl/counter.vhdl
-- Adapted from: https://en.wikipedia.org/wiki/VHDL#Example:_a_counter

library ieee;
use ieee.std_logic_1164.all;
use ieee.numeric_std.all; -- unsigned

entity counter is
    generic (
        width : in natural := 2
    );
    port (
        rst, clk, load : in std_logic;
        data : in std_logic_vector(width-1 downto 0);
        count : out std_logic_vector(width-1 downto 0)
    );
end entity counter;

architecture rtl of counter is
    signal cnt : unsigned(width-1 downto 0);
begin
    process(rst, clk) is
    begin
        if rst = '1' then
            cnt <= (others => '0');
        elsif rising_edge(clk) then
            if load = '1' then
                cnt <= unsigned(data);
            else
                cnt <= cnt + 1;
            end if;
        end if;
    end process;
    count <= std_logic_vector(cnt);
end architecture rtl;

vhdl/counter_tb.vhdl
library ieee;
use ieee.std_logic_1164.all;
library std;
use std.textio.all;

use work.common.all;

entity counter_tb is
end counter_tb;

architecture behav of counter_tb is
    constant width : natural := 2;

    signal rst, load : std_logic := '0';
    signal clk : std_logic := '0';
    signal data : std_logic_vector(width-1 downto 0);
    signal count : std_logic_vector(width-1 downto 0);

    type io_t is record
        load : std_logic;
        data : std_logic_vector(width-1 downto 0);
        count : std_logic_vector(width-1 downto 0);
    end record;
    type ios_t is array (natural range <>) of io_t;
    constant ios : ios_t := (
        ('1', "00", "00"),
        ('0', "UU", "01"),
        ('0', "UU", "10"),
        ('0', "UU", "11"),

        ('1', "10", "10"),
        ('0', "UU", "11"),
        ('0', "UU", "00"),
        ('0', "UU", "01")
    );
begin
    counter_0: entity work.counter port map (rst, clk, load, data, count);

    process
    begin
        for i in ios'range loop
            load <= ios(i).load;
            data <= ios(i).data;
            wait until falling_edge(clk);
            assert count = ios(i).count;
        end loop;
        wait;
    end process;

    process
    begin
        for i in 1 to 2 * ios'length loop
            wait for common_clk_period / 2;
            clk <= not clk;
        end loop;
        wait;
    end process;

end behav;

_raw/vhdl/counter.vcd
$date
  Tue Aug 16 16:02:30 2022
$end
$version
  GHDL v0
$end
$timescale
  1 fs
$end
$scope module standard $end
$upscope $end
$scope module textio $end
$upscope $end
$scope module std_logic_1164 $end
$upscope $end
$scope module common $end
$upscope $end
$scope module numeric_std $end
$upscope $end
$scope module counter_tb $end
$var reg 1 ! rst $end
$var reg 1 " load $end
$var reg 1 # clk $end
$var reg 2 $ data[1:0] $end
$var reg 2 % count[1:0] $end
$scope module counter_0 $end
$var reg 1 & rst $end
$var reg 1 ' clk $end
$var reg 1 ( load $end
$var reg 2 ) data[1:0] $end
$var reg 2 * count[1:0] $end
$var reg 2 + cnt[1:0] $end
$upscope $end
$upscope $end
$enddefinitions $end
#0
0!
1"
0#
b00 $
bUU %
0&
0'
1(
b00 )
bUU *
bUU +
#500000
1#
b00 %
1'
b00 *
b00 +
#1000000
0"
0#
bUU $
0'
0(
bUU )
#1500000
1#
b01 %
1'
b01 *
b01 +
#2000000
0#
0'
#2500000
1#
b10 %
1'
b10 *
b10 +
#3000000
0#
0'
#3500000
1#
b11 %
1'
b11 *
b11 +
#4000000
1"
0#
b10 $
0'
1(
b10 )
#4500000
1#
b10 %
1'
b10 *
b10 +
#5000000
0"
0#
bUU $
0'
0(
bUU )
#5500000
1#
b11 %
1'
b11 *
b11 +
#6000000
0#
0'
#6500000
1#
b00 %
1'
b00 *
b00 +
#7000000
0#
0'
#7500000
1#
b01 %
1'
b01 *
b01 +
