vhdl/adder.vhdl
-- 1 bit adder.

entity adder is
  port (i0, i1, ci : in bit; s, co : out bit);
end adder;

architecture rtl of adder is
begin
   s <= i0 xor i1 xor ci;
   co <= (i0 and i1) or (i0 and ci) or (i1 and ci);
end rtl;

_raw/vhdl/adder_tb.vhdl
entity adder_tb is
end adder_tb;

use work.common.all;

architecture behav of adder_tb is
    signal i0, i1, ci, s, co : bit;
begin
    adder_0: entity work.adder port map (i0, i1, ci, s, co);
    process
        type pattern_type is record
            i0, i1, ci, s, co : bit;
        end record;
        type pattern_array is array (natural range <>) of pattern_type;
        constant patterns : pattern_array := (
            ('0', '0', '0', '0', '0'),
            ('0', '0', '1', '1', '0'),
            ('0', '1', '0', '1', '0'),
            ('0', '1', '1', '0', '1'),
            ('1', '0', '0', '1', '0'),
            ('1', '0', '1', '0', '1'),
            ('1', '1', '0', '0', '1'),
            ('1', '1', '1', '1', '1')
        );
    begin
        for i in patterns'range loop
            i0 <= patterns(i).i0;
            i1 <= patterns(i).i1;
            ci <= patterns(i).ci;
            wait for common_clk_period;
            assert s = patterns(i).s;
            assert co = patterns(i).co;
        end loop;
        wait;
    end process;
end behav;

vhdl/adder.vcd
$date
  Tue Aug 16 16:02:30 2022
$end
$version
  GHDL v0
$end
$timescale
  1 fs
$end
$scope module standard $end
$upscope $end
$scope module common $end
$upscope $end
$scope module adder_tb $end
$var reg 1 ! i0 $end
$var reg 1 " i1 $end
$var reg 1 # ci $end
$var reg 1 $ s $end
$var reg 1 % co $end
$scope module adder_0 $end
$var reg 1 & i0 $end
$var reg 1 ' i1 $end
$var reg 1 ( ci $end
$var reg 1 ) s $end
$var reg 1 * co $end
$upscope $end
$upscope $end
$enddefinitions $end
#0
0!
0"
0#
0$
0%
0&
0'
0(
0)
0*
#1000000
1#
1$
1(
1)
#2000000
1"
0#
1'
0(
#3000000
1#
0$
1%
1(
0)
1*
#4000000
1!
0"
0#
1$
0%
1&
0'
0(
1)
0*
#5000000
1#
0$
1%
1(
0)
1*
#6000000
1"
0#
1'
0(
#7000000
1#
1$
1(
1)
